{
  "ckpt": "ckpts_v3/C1_scratch/draft.pt",
  "C": null,
  "gamma": 5,
  "max_new": 32,
  "skip": 5000,
  "per_domain": 50,
  "seeds": [
    0,
    1
  ],
  "results": {
    "math": {
      "mean_tau": 1.9198334193326454,
      "norm_tau": 0.3199722365554409,
      "n_prompts": 50,
      "n_seeds": 2,
      "tau_by_prompt_seed": [
        [
          2.0625,
          2.0
        ],
        [
          1.736842105263158,
          1.6842105263157894
        ],
        [
          1.6842105263157894,
          2.1333333333333333
        ],
        [
          1.736842105263158,
          1.736842105263158
        ],
        [
          2.1333333333333333,
          1.6842105263157894
        ],
        [
          1.8823529411764706,
          1.7777777777777777
        ],
        [
          1.8823529411764706,
          2.2857142857142856
        ],
        [
          2.0,
          2.0
        ],
        [
          1.7894736842105263,
          1.7777777777777777
        ],
        [
          2.0,
          2.0625
        ],
        [
          1.8888888888888888,
          1.736842105263158
        ],
        [
          1.7894736842105263,
          1.7894736842105263
        ],
        [
          1.7777777777777777,
          1.6842105263157894
        ],
        [
          2.0625,
          2.0625
        ],
        [
          1.7777777777777777,
          1.9411764705882353
        ],
        [
          2.0555555555555554,
          2.0588235294117645
        ],
        [
          2.0,
          1.8823529411764706
        ],
        [
          1.9411764705882353,
          1.8823529411764706
        ],
        [
          1.9411764705882353,
          1.8823529411764706
        ],
        [
          2.1333333333333333,
          1.8823529411764706
        ],
        [
          1.7777777777777777,
          1.8823529411764706
        ],
        [
          1.6842105263157894,
          2.2
        ],
        [
          1.65,
          1.9411764705882353
        ],
        [
          1.8333333333333333,
          2.25
        ],
        [
          1.6,
          1.7777777777777777
        ],
        [
          1.8823529411764706,
          1.7777777777777777
        ],
        [
          1.7894736842105263,
          2.0
        ],
        [
          1.8823529411764706,
          1.8823529411764706
        ],
        [
          2.0,
          2.1333333333333333
        ],
        [
          2.0,
          1.9411764705882353
        ],
        [
          2.1333333333333333,
          2.2666666666666666
        ],
        [
          1.8823529411764706,
          2.0
        ],
        [
          2.0,
          2.357142857142857
        ],
        [
          1.7777777777777777,
          1.5238095238095237
        ],
        [
          1.7894736842105263,
          2.0
        ],
        [
          2.0,
          1.7894736842105263
        ],
        [
          1.6,
          1.6842105263157894
        ],
        [
          1.9411764705882353,
          1.7777777777777777
        ],
        [
          2.1333333333333333,
          1.8823529411764706
        ],
        [
          1.7777777777777777,
          2.1333333333333333
        ],
        [
          2.0,
          2.1333333333333333
        ],
        [
          2.0,
          1.9411764705882353
        ],
        [
          2.0,
          1.8888888888888888
        ],
        [
          2.0625,
          1.8333333333333333
        ],
        [
          2.0625,
          2.125
        ],
        [
          1.8333333333333333,
          2.0
        ],
        [
          2.0625,
          1.8333333333333333
        ],
        [
          1.7777777777777777,
          2.1333333333333333
        ],
        [
          2.0625,
          1.9411764705882353
        ],
        [
          1.736842105263158,
          2.0
        ]
      ],
      "position_acceptance": [
        0.5163360560093349,
        0.5740112994350283,
        0.281496062992126,
        0.0979020979020979,
        0.2857142857142857
      ],
      "latency_ms": {
        "t_anchor": 251.4966971523418,
        "t_draft": 14.808695091482344,
        "t_verify": 253.07170868297152,
        "rounds": 1714,
        "gen_tokens": 3268.0,
        "L_offline_ms_per_tok": 272.40280018008804
      }
    },
    "code": {
      "mean_tau": 1.8705239385227777,
      "norm_tau": 0.31175398975379626,
      "n_prompts": 50,
      "n_seeds": 2,
      "tau_by_prompt_seed": [
        [
          2.125,
          2.0
        ],
        [
          1.8888888888888888,
          2.1333333333333333
        ],
        [
          2.0,
          2.1333333333333333
        ],
        [
          2.125,
          2.2
        ],
        [
          1.8333333333333333,
          1.736842105263158
        ],
        [
          2.0,
          1.7777777777777777
        ],
        [
          1.65,
          1.9411764705882353
        ],
        [
          1.7777777777777777,
          1.8823529411764706
        ],
        [
          1.65,
          1.736842105263158
        ],
        [
          1.7777777777777777,
          1.7777777777777777
        ],
        [
          1.8823529411764706,
          1.8823529411764706
        ],
        [
          1.6,
          1.7894736842105263
        ],
        [
          1.8823529411764706,
          1.8823529411764706
        ],
        [
          1.8333333333333333,
          2.0
        ],
        [
          1.7777777777777777,
          1.6842105263157894
        ],
        [
          1.8888888888888888,
          1.8333333333333333
        ],
        [
          1.8823529411764706,
          2.0
        ],
        [
          1.6842105263157894,
          2.0
        ],
        [
          1.7894736842105263,
          1.6
        ],
        [
          1.9411764705882353,
          1.8333333333333333
        ],
        [
          1.5714285714285714,
          1.65
        ],
        [
          1.65,
          1.8823529411764706
        ],
        [
          1.8823529411764706,
          2.125
        ],
        [
          1.8823529411764706,
          1.8888888888888888
        ],
        [
          2.0,
          2.1875
        ],
        [
          2.0,
          2.125
        ],
        [
          2.357142857142857,
          2.2
        ],
        [
          2.1333333333333333,
          1.8823529411764706
        ],
        [
          1.8888888888888888,
          1.9411764705882353
        ],
        [
          1.8823529411764706,
          1.7
        ],
        [
          1.8333333333333333,
          1.736842105263158
        ],
        [
          1.5238095238095237,
          1.6842105263157894
        ],
        [
          1.6,
          1.6842105263157894
        ],
        [
          1.6842105263157894,
          1.8823529411764706
        ],
        [
          2.0,
          2.2666666666666666
        ],
        [
          1.7,
          1.8888888888888888
        ],
        [
          1.8333333333333333,
          1.8888888888888888
        ],
        [
          1.7777777777777777,
          1.8823529411764706
        ],
        [
          1.8333333333333333,
          1.6842105263157894
        ],
        [
          1.8823529411764706,
          1.7777777777777777
        ],
        [
          1.9411764705882353,
          2.0625
        ],
        [
          1.7,
          1.6
        ],
        [
          1.8823529411764706,
          1.8823529411764706
        ],
        [
          2.0625,
          1.9411764705882353
        ],
        [
          1.9411764705882353,
          2.0625
        ],
        [
          1.6842105263157894,
          1.8333333333333333
        ],
        [
          1.65,
          1.6842105263157894
        ],
        [
          1.736842105263158,
          1.8333333333333333
        ],
        [
          1.8888888888888888,
          2.125
        ],
        [
          2.0625,
          1.7894736842105263
        ]
      ],
      "position_acceptance": [
        0.5206798866855524,
        0.4961915125136017,
        0.2719298245614035,
        0.10483870967741936,
        0.0
      ],
      "latency_ms": {
        "t_anchor": 202.68908351140027,
        "t_draft": 14.71813378872735,
        "t_verify": 211.25159171537203,
        "rounds": 1765,
        "gen_tokens": 3277.0,
        "L_offline_ms_per_tok": 230.87665484051172
      }
    },
    "chat": {
      "mean_tau": 1.82434445065038,
      "norm_tau": 0.30405740844173,
      "n_prompts": 50,
      "n_seeds": 2,
      "tau_by_prompt_seed": [
        [
          1.6666666666666667,
          1.5238095238095237
        ],
        [
          2.0,
          1.8888888888888888
        ],
        [
          1.65,
          1.65
        ],
        [
          1.7894736842105263,
          1.736842105263158
        ],
        [
          1.391304347826087,
          1.4545454545454546
        ],
        [
          2.0,
          2.0
        ],
        [
          1.6842105263157894,
          1.619047619047619
        ],
        [
          1.7777777777777777,
          1.9411764705882353
        ],
        [
          1.6842105263157894,
          1.75
        ],
        [
          1.8888888888888888,
          1.8823529411764706
        ],
        [
          1.6,
          1.6
        ],
        [
          1.6,
          1.6
        ],
        [
          2.0625,
          1.736842105263158
        ],
        [
          1.8823529411764706,
          1.8823529411764706
        ],
        [
          2.4,
          1.8823529411764706
        ],
        [
          1.9411764705882353,
          1.7777777777777777
        ],
        [
          1.8333333333333333,
          1.9411764705882353
        ],
        [
          1.7777777777777777,
          1.6842105263157894
        ],
        [
          1.7777777777777777,
          1.8333333333333333
        ],
        [
          1.8333333333333333,
          1.65
        ],
        [
          2.0625,
          1.8823529411764706
        ],
        [
          1.8888888888888888,
          1.9411764705882353
        ],
        [
          1.9411764705882353,
          1.7777777777777777
        ],
        [
          1.8823529411764706,
          2.0
        ],
        [
          1.7777777777777777,
          1.6842105263157894
        ],
        [
          1.7777777777777777,
          1.8823529411764706
        ],
        [
          2.0,
          2.0
        ],
        [
          1.8823529411764706,
          2.0
        ],
        [
          1.6,
          1.6
        ],
        [
          1.65,
          1.6
        ],
        [
          1.7894736842105263,
          1.8888888888888888
        ],
        [
          2.0625,
          1.8333333333333333
        ],
        [
          2.0625,
          2.2
        ],
        [
          1.6842105263157894,
          1.6842105263157894
        ],
        [
          1.65,
          1.8823529411764706
        ],
        [
          1.736842105263158,
          1.8333333333333333
        ],
        [
          1.65,
          1.7894736842105263
        ],
        [
          2.357142857142857,
          2.0
        ],
        [
          2.2,
          2.0625
        ],
        [
          1.8823529411764706,
          2.0
        ],
        [
          1.7777777777777777,
          2.0
        ],
        [
          1.65,
          1.6842105263157894
        ],
        [
          1.736842105263158,
          1.6842105263157894
        ],
        [
          1.619047619047619,
          1.8333333333333333
        ],
        [
          2.0,
          1.8823529411764706
        ],
        [
          1.6842105263157894,
          1.7777777777777777
        ],
        [
          1.9411764705882353,
          1.8421052631578947
        ],
        [
          2.0625,
          1.8823529411764706
        ],
        [
          1.65,
          1.6
        ],
        [
          1.8888888888888888,
          1.8823529411764706
        ]
      ],
      "position_acceptance": [
        0.5011049723756906,
        0.4785005512679162,
        0.2465437788018433,
        0.12149532710280374,
        0.23076923076923078
      ],
      "latency_ms": {
        "t_anchor": 195.11802846611508,
        "t_draft": 14.555152017206407,
        "t_verify": 204.16497569756314,
        "rounds": 1810,
        "gen_tokens": 3274.0,
        "L_offline_ms_per_tok": 228.78651884160087
      }
    },
    "prose": {
      "mean_tau": 1.7032381232268128,
      "norm_tau": 0.2838730205378021,
      "n_prompts": 50,
      "n_seeds": 2,
      "tau_by_prompt_seed": [
        [
          1.5714285714285714,
          1.8333333333333333
        ],
        [
          1.434782608695652,
          1.9411764705882353
        ],
        [
          1.736842105263158,
          2.0
        ],
        [
          1.8823529411764706,
          1.8823529411764706
        ],
        [
          1.5217391304347827,
          1.7894736842105263
        ],
        [
          1.4545454545454546,
          1.391304347826087
        ],
        [
          1.65,
          1.5714285714285714
        ],
        [
          1.6842105263157894,
          1.5454545454545454
        ],
        [
          1.8823529411764706,
          1.4545454545454546
        ],
        [
          1.7894736842105263,
          1.7
        ],
        [
          1.3333333333333333,
          2.0
        ],
        [
          1.6842105263157894,
          1.5714285714285714
        ],
        [
          1.3333333333333333,
          1.7777777777777777
        ],
        [
          1.375,
          1.7
        ],
        [
          1.8333333333333333,
          1.6842105263157894
        ],
        [
          1.5714285714285714,
          1.736842105263158
        ],
        [
          1.375,
          1.391304347826087
        ],
        [
          1.3333333333333333,
          1.65
        ],
        [
          1.28,
          1.65
        ],
        [
          1.3333333333333333,
          1.7777777777777777
        ],
        [
          1.6842105263157894,
          1.5714285714285714
        ],
        [
          1.5454545454545454,
          1.28
        ],
        [
          1.6,
          1.4545454545454546
        ],
        [
          1.1851851851851851,
          1.6842105263157894
        ],
        [
          1.736842105263158,
          1.7777777777777777
        ],
        [
          2.0,
          1.9444444444444444
        ],
        [
          1.5238095238095237,
          1.8823529411764706
        ],
        [
          1.6842105263157894,
          1.5454545454545454
        ],
        [
          1.3333333333333333,
          1.32
        ],
        [
          2.125,
          2.125
        ],
        [
          2.4285714285714284,
          2.3125
        ],
        [
          1.28,
          1.5
        ],
        [
          1.4545454545454546,
          1.6842105263157894
        ],
        [
          1.6842105263157894,
          1.2307692307692308
        ],
        [
          1.5238095238095237,
          1.5238095238095237
        ],
        [
          1.1851851851851851,
          1.4545454545454546
        ],
        [
          1.7777777777777777,
          1.9411764705882353
        ],
        [
          1.619047619047619,
          1.1851851851851851
        ],
        [
          1.3333333333333333,
          1.391304347826087
        ],
        [
          1.5238095238095237,
          1.2307692307692308
        ],
        [
          1.6,
          1.6
        ],
        [
          1.6,
          1.7777777777777777
        ],
        [
          1.9411764705882353,
          1.7894736842105263
        ],
        [
          1.8823529411764706,
          2.0
        ],
        [
          2.2857142857142856,
          2.0
        ],
        [
          1.3333333333333333,
          1.8333333333333333
        ],
        [
          1.65,
          1.736842105263158
        ],
        [
          1.6842105263157894,
          1.7777777777777777
        ],
        [
          3.4,
          3.5555555555555554
        ],
        [
          2.6666666666666665,
          2.8333333333333335
        ]
      ],
      "position_acceptance": [
        0.410140562248996,
        0.37454100367197063,
        0.27450980392156865,
        0.5238095238095238,
        0.5
      ],
      "latency_ms": {
        "t_anchor": 256.5333756479871,
        "t_draft": 14.311513843926056,
        "t_verify": 258.6011566844641,
        "rounds": 1992,
        "gen_tokens": 3265.0,
        "L_offline_ms_per_tok": 323.0188434864758
      }
    },
    "macro_avg_tau": 1.8294849829331539
  }
}